client_encryption/__init__.py
client_encryption/api_encryption.py
client_encryption/encoding_utils.py
client_encryption/encryption_exception.py
client_encryption/encryption_utils.py
client_encryption/field_level_encryption.py
client_encryption/field_level_encryption_config.py
client_encryption/json_path_utils.py
client_encryption/jwe_encryption.py
client_encryption/jwe_encryption_config.py
client_encryption/session_key_params.py
client_encryption/version.py
mastercard_client_encryption-1.23.3.dist-info/LICENSE
mastercard_client_encryption-1.23.3.dist-info/METADATA
mastercard_client_encryption-1.23.3.dist-info/WHEEL
mastercard_client_encryption-1.23.3.dist-info/top_level.txt
mastercard_client_encryption-1.23.3.dist-info/RECORD
