Metadata-Version: 2.1
Name: mastercard-client-encryption
Version: 1.23.3
Summary: Mastercard Client encryption.
Home-page: https://github.com/Mastercard/client-encryption-python
Author: Mastercard
License: MIT
Classifier: Development Status :: 5 - Production/Stable
Classifier: Intended Audience :: Developers
Classifier: Natural Language :: English
Classifier: Operating System :: OS Independent
Classifier: Programming Language :: Python :: 3.8
Classifier: Programming Language :: Python :: 3.9
Classifier: Topic :: Software Development :: Libraries :: Python Modules
Requires-Python: >=3.8
License-File: LICENSE
Requires-Dist: pycryptodome >=3.8.1
Requires-Dist: setuptools >=69.1.0
Requires-Dist: cryptography >=42.0.0
